Metadata-Version: 2.1
Name: actuarialCalculations
Version: 1.0.1
Summary: UNKNOWN
Home-page: https://github.com/francose/acturialcalculations
Author: Sadik Erisen
Author-email: fserisen@gmail.com
License: UNKNOWN
Download-URL: https://github.com/francose/acturialcalculations/archive/master.zip
Keywords: finance,annuity calculations,actuarial math,financial math,amortization schedule,sinking fund,present value,accumulated value
Platform: UNKNOWN
Classifier: Development Status :: 5 - Production/Stable
Classifier: Intended Audience :: Developers
Classifier: Topic :: Office/Business :: Financial
Classifier: License :: OSI Approved :: MIT License
Classifier: Programming Language :: Python :: 3.6
Classifier: Programming Language :: Python :: 3.7
